grax/__init__.py
grax/core.py
grax-0.1.0.dist-info/METADATA
grax-0.1.0.dist-info/WHEEL
grax-0.1.0.dist-info/top_level.txt
grax-0.1.0.dist-info/RECORD
