Metadata-Version: 2.4
Name: grax
Version: 0.1.0
Summary: GRAX transforms geospatial shapefiles into machine-learning-ready graph networks—automating the conversion from raw GIS data to topologically accurate NetworkX graphs for GNNs, CNA, and digital twin applications.
Home-page: https://github.com/real-ahmed-moussa/grax
Author: Dr. Ahmed Moussa
Author-email: ahmedyosrihamdy@gmail.com
License: MIT
Classifier: Programming Language :: Python :: 3
Classifier: License :: OSI Approved :: MIT License
Classifier: Operating System :: OS Independent
Classifier: Topic :: Scientific/Engineering :: Artificial Intelligence
Requires-Python: >=3.7
Requires-Dist: numpy
Requires-Dist: fiona
Requires-Dist: networkx
Requires-Dist: shapely
Dynamic: author
Dynamic: author-email
Dynamic: classifier
Dynamic: description
Dynamic: description-content-type
Dynamic: home-page
Dynamic: license
Dynamic: requires-dist
Dynamic: requires-python
Dynamic: summary
